fsm-assignments/problem2_traffic/traffic_light.v
module traffic_light(
  input  wire clk,
  input  wire rst, //sync active-high
  input  wire tick, //1-cycle per-second pulse
  output reg  ns_g, ns_y, ns_r,
  output reg  ew_g, ew_y, ew_r
);

  // State encoding
  parameter S_NS_G = 2'b00;  // North-South Green
  parameter S_NS_Y = 2'b01;  // North-South Yellow
  parameter S_EW_G = 2'b10;  // East-West Green
  parameter S_EW_Y = 2'b11;  // East-West Yellow

  reg [1:0] state, next_state;   // FSM current and next state
  reg [2:0] tick_count;          // To count ticks within each state (up to 5)

  // State register (sequential block)
  always @(posedge clk) begin
    if (rst) begin
      state <= S_NS_G;
      tick_count <= 0;   // On reset, start with NS green and clear tick counter
    end else state <= next_state;  // Normal operation: move to next state
  end

  // Tick counter (duration control)
  always @(posedge clk) begin
    if (rst) tick_count <= 0;   // reset counter
    else if (tick) begin
      case (state)
        // Stay in NS green for 5 ticks
        S_NS_G: tick_count <= (tick_count == 4) ? 0 : tick_count + 1;
        // Stay in NS yellow for 2 ticks
        S_NS_Y: tick_count <= (tick_count == 1) ? 0 : tick_count + 1;
        // Stay in EW green for 5 ticks
        S_EW_G: tick_count <= (tick_count == 4) ? 0 : tick_count + 1;
        // Stay in EW yellow for 2 ticks
        S_EW_Y: tick_count <= (tick_count == 1) ? 0 : tick_count + 1;
      endcase
    end
  end

  // Next-state logic
  always @(*) begin
    next_state = state;   // default: hold state
    case (state)
      // After 5 ticks in NS green → go to NS yellow
      S_NS_G: if (tick && tick_count == 4) next_state = S_NS_Y;
      // After 2 ticks in NS yellow → go to EW green
      S_NS_Y: if (tick && tick_count == 1) next_state = S_EW_G;
      // After 5 ticks in EW green → go to EW yellow
      S_EW_G: if (tick && tick_count == 4) next_state = S_EW_Y;
      // After 2 ticks in EW yellow → go back to NS green
      S_EW_Y: if (tick && tick_count == 1) next_state = S_NS_G;
    endcase
  end

  // Output logic (Moore machine)
  // Lights are based only on the current state

  always @(*) begin
    // Default all lights off
    ns_g = 0; ns_y = 0; ns_r = 0;
    ew_g = 0; ew_y = 0; ew_r = 0;

    case (state)
      // NS = Green, EW = Red
      S_NS_G: begin
        ns_g = 1; ew_r = 1;
      end
      // NS = Yellow, EW = Red
      S_NS_Y: begin
        ns_y = 1; ew_r = 1;
      end
      // EW = Green, NS = Red
      S_EW_G: begin
        ew_g = 1; ns_r = 1;
      end
      // EW = Yellow, NS = Red
      S_EW_Y: begin
        ew_y = 1; ns_r = 1;
      end
    endcase
  end

endmodule

fsm-assignments/problem2_traffic/tb_traffic_light.v
`timescale 1ns/1ps

module tb_traffic_light;
  reg clk, rst;
  wire tick;
  wire ns_g, ns_y, ns_r, ew_g, ew_y, ew_r;

  // Instantiate fake prescaler for simulation
  reg [4:0] cyc;
  reg tick_reg;
  assign tick = tick_reg;

  always @(posedge clk) begin
      cyc <= cyc + 1;
      tick_reg <= (cyc % 5 == 0); // 1 tick every 20 cycles
  end

  traffic_light dut(
      .clk(clk), .rst(rst), .tick(tick),
      .ns_g(ns_g), .ns_y(ns_y), .ns_r(ns_r),
      .ew_g(ew_g), .ew_y(ew_y), .ew_r(ew_r)
  ); //DUT

  // Clock: 10ns period (100 MHz)
  always #5 clk = ~clk;

  initial begin
    $dumpfile("traffic_light.vcd");
    $dumpvars(0, tb_traffic_light);

    clk  = 0;
    rst  = 1;
    cyc  = 0;
    tick_reg = 0;

    // Reset
    repeat (2) @(posedge clk);
    rst = 0;

    // Run for ~60 ticks (~4 full cycles)
    repeat (1200) @(posedge clk);

    $stop;
  end
endmodule

fsm-assignments/problem2_traffic/waves/traffic_light.vcd
$date
	Tue Aug 19 11:17:45 2025
$end
$version
	Icarus Verilog
$end
$timescale
	1ps
$end
$scope module tb_traffic_light $end
$var wire 1 ! ew_g $end
$var wire 1 " ew_r $end
$var wire 1 # ew_y $end
$var wire 1 $ ns_g $end
$var wire 1 % ns_r $end
$var wire 1 & ns_y $end
$var wire 1 ' tick $end
$var reg 1 ( clk $end
$var reg 5 ) cyc [4:0] $end
$var reg 1 * rst $end
$var reg 1 + tick_reg $end
$scope module dut $end
$var wire 1 , clk $end
$var wire 1 - rst $end
$var wire 1 ' tick $end
$var reg 1 . ew_g $end
$var reg 1 / ew_r $end
$var reg 1 0 ew_y $end
$var reg 2 1 next_state [1:0] $end
$var reg 1 2 ns_g $end
$var reg 1 3 ns_r $end
$var reg 1 4 ns_y $end
$var reg 2 5 state [1:0] $end
$var reg 3 6 tick_count [2:0] $end
$upscope $end
$upscope $end
$enddefinitions $end
#0
$dumpvars
bx 6
bx 5
x4
x3
x2
bx 1
x0
x/
x.
1-
0,
0+
1*
b0 )
0(
0'
x&
x%
x$
x#
x"
x!
$end
#5000
1/
1"
00
0#
0.
0!
03
0%
04
0&
12
1$
b0 1
b0 5
b0 6
1+
1'
b1 )
1(
1,
#10000
0(
0,
#15000
0+
0'
b10 )
0*
0-
1(
1,
#20000
0(
0,
#25000
b11 )
1(
1,
#30000
0(
0,
#35000
b100 )
1(
1,
#40000
0(
0,
#45000
b101 )
1(
1,
#50000
0(
0,
#55000
1+
1'
b110 )
1(
1,
#60000
0(
0,
#65000
b1 6
0+
0'
b111 )
1(
1,
#70000
0(
0,
#75000
b1000 )
1(
1,
#80000
0(
0,
#85000
b1001 )
1(
1,
#90000
0(
0,
#95000
b1010 )
1(
1,
#100000
0(
0,
#105000
1+
1'
b1011 )
1(
1,
#110000
0(
0,
#115000
0+
0'
b1100 )
b10 6
1(
1,
#120000
0(
0,
#125000
b1101 )
1(
1,
#130000
0(
0,
#135000
b1110 )
1(
1,
#140000
0(
0,
#145000
b1111 )
1(
1,
#150000
0(
0,
#155000
1+
1'
b10000 )
1(
1,
#160000
0(
0,
#165000
b11 6
0+
0'
b10001 )
1(
1,
#170000
0(
0,
#175000
b10010 )
1(
1,
#180000
0(
0,
#185000
b10011 )
1(
1,
#190000
0(
0,
#195000
b10100 )
1(
1,
#200000
0(
0,
#205000
1+
1'
b10101 )
1(
1,
#210000
0(
0,
#215000
0+
0'
b10110 )
b100 6
1(
1,
#220000
0(
0,
#225000
b10111 )
1(
1,
#230000
0(
0,
#235000
b11000 )
1(
1,
#240000
0(
0,
#245000
b11001 )
1(
1,
#250000
0(
0,
#255000
b1 1
1+
1'
b11010 )
1(
1,
#260000
0(
0,
#265000
14
1&
1/
1"
02
0$
b1 5
b0 6
0+
0'
b11011 )
1(
1,
#270000
0(
0,
#275000
b11100 )
1(
1,
#280000
0(
0,
#285000
b11101 )
1(
1,
#290000
0(
0,
#295000
b11110 )
1(
1,
#300000
0(
0,
#305000
1+
1'
b11111 )
1(
1,
#310000
0(
0,
#315000
0+
0'
b0 )
b1 6
1(
1,
#320000
0(
0,
#325000
b10 1
1+
1'
b1 )
1(
1,
#330000
0(
0,
#335000
13
1%
1.
1!
0/
0"
04
0&
0+
0'
b10 )
b0 6
b10 5
1(
1,
#340000
0(
0,
#345000
b11 )
1(
1,
#350000
0(
0,
#355000
b100 )
1(
1,
#360000
0(
0,
#365000
b101 )
1(
1,
#370000
0(
0,
#375000
1+
1'
b110 )
1(
1,
#380000
0(
0,
#385000
b1 6
0+
0'
b111 )
1(
1,
#390000
0(
0,
#395000
b1000 )
1(
1,
#400000
0(
0,
#405000
b1001 )
1(
1,
#410000
0(
0,
#415000
b1010 )
1(
1,
#420000
0(
0,
#425000
1+
1'
b1011 )
1(
1,
#430000
0(
0,
#435000
0+
0'
b1100 )
b10 6
1(
1,
#440000
0(
0,
#445000
b1101 )
1(
1,
#450000
0(
0,
#455000
b1110 )
1(
1,
#460000
0(
0,
#465000
b1111 )
1(
1,
#470000
0(
0,
#475000
1+
1'
b10000 )
1(
1,
#480000
0(
0,
#485000
b11 6
0+
0'
b10001 )
1(
1,
#490000
0(
0,
#495000
b10010 )
1(
1,
#500000
0(
0,
#505000
b10011 )
1(
1,
#510000
0(
0,
#515000
b10100 )
1(
1,
#520000
0(
0,
#525000
1+
1'
b10101 )
1(
1,
#530000
0(
0,
#535000
0+
0'
b10110 )
b100 6
1(
1,
#540000
0(
0,
#545000
b10111 )
1(
1,
#550000
0(
0,
#555000
b11000 )
1(
1,
#560000
0(
0,
#565000
b11001 )
1(
1,
#570000
0(
0,
#575000
b11 1
1+
1'
b11010 )
1(
1,
#580000
0(
0,
#585000
10
1#
0.
0!
13
1%
b11 5
b0 6
0+
0'
b11011 )
1(
1,
#590000
0(
0,
#595000
b11100 )
1(
1,
#600000
0(
0,
#605000
b11101 )
1(
1,
#610000
0(
0,
#615000
b11110 )
1(
1,
#620000
0(
0,
#625000
1+
1'
b11111 )
1(
1,
#630000
0(
0,
#635000
0+
0'
b0 )
b1 6
1(
1,
#640000
0(
0,
#645000
b0 1
1+
1'
b1 )
1(
1,
#650000
0(
0,
#655000
1/
1"
12
1$
00
0#
03
0%
0+
0'
b10 )
b0 6
b0 5
1(
1,
#660000
0(
0,
#665000
b11 )
1(
1,
#670000
0(
0,
#675000
b100 )
1(
1,
#680000
0(
0,
#685000
b101 )
1(
1,
#690000
0(
0,
#695000
1+
1'
b110 )
1(
1,
#700000
0(
0,
#705000
b1 6
0+
0'
b111 )
1(
1,
#710000
0(
0,
#715000
b1000 )
1(
1,
#720000
0(
0,
#725000
b1001 )
1(
1,
#730000
0(
0,
#735000
b1010 )
1(
1,
#740000
0(
0,
#745000
1+
1'
b1011 )
1(
1,
#750000
0(
0,
#755000
0+
0'
b1100 )
b10 6
1(
1,
#760000
0(
0,
#765000
b1101 )
1(
1,
#770000
0(
0,
#775000
b1110 )
1(
1,
#780000
0(
0,
#785000
b1111 )
1(
1,
#790000
0(
0,
#795000
1+
1'
b10000 )
1(
1,
#800000
0(
0,
#805000
b11 6
0+
0'
b10001 )
1(
1,
#810000
0(
0,
#815000
b10010 )
1(
1,
#820000
0(
0,
#825000
b10011 )
1(
1,
#830000
0(
0,
#835000
b10100 )
1(
1,
#840000
0(
0,
#845000
1+
1'
b10101 )
1(
1,
#850000
0(
0,
#855000
0+
0'
b10110 )
b100 6
1(
1,
#860000
0(
0,
#865000
b10111 )
1(
1,
#870000
0(
0,
#875000
b11000 )
1(
1,
#880000
0(
0,
#885000
b11001 )
1(
1,
#890000
0(
0,
#895000
b1 1
1+
1'
b11010 )
1(
1,
#900000
0(
0,
#905000
14
1&
1/
1"
02
0$
b1 5
b0 6
0+
0'
b11011 )
1(
1,
#910000
0(
0,
#915000
b11100 )
1(
1,
#920000
0(
0,
#925000
b11101 )
1(
1,
#930000
0(
0,
#935000
b11110 )
1(
1,
#940000
0(
0,
#945000
1+
1'
b11111 )
1(
1,
#950000
0(
0,
#955000
0+
0'
b0 )
b1 6
1(
1,
#960000
0(
0,
#965000
b10 1
1+
1'
b1 )
1(
1,
#970000
0(
0,
#975000
13
1%
1.
1!
0/
0"
04
0&
0+
0'
b10 )
b0 6
b10 5
1(
1,
#980000
0(
0,
#985000
b11 )
1(
1,
#990000
0(
0,
#995000
b100 )
1(
1,
#1000000
0(
0,
#1005000
b101 )
1(
1,
#1010000
0(
0,
#1015000
1+
1'
b110 )
1(
1,
#1020000
0(
0,
#1025000
b1 6
0+
0'
b111 )
1(
1,
#1030000
0(
0,
#1035000
b1000 )
1(
1,
#1040000
0(
0,
#1045000
b1001 )
1(
1,
#1050000
0(
0,
#1055000
b1010 )
1(
1,
#1060000
0(
0,
#1065000
1+
1'
b1011 )
1(
1,
#1070000
0(
0,
#1075000
0+
0'
b1100 )
b10 6
1(
1,
#1080000
0(
0,
#1085000
b1101 )
1(
1,
#1090000
0(
0,
#1095000
b1110 )
1(
1,
#1100000
0(
0,
#1105000
b1111 )
1(
1,
#1110000
0(
0,
#1115000
1+
1'
b10000 )
1(
1,
#1120000
0(
0,
#1125000
b11 6
0+
0'
b10001 )
1(
1,
#1130000
0(
0,
#1135000
b10010 )
1(
1,
#1140000
0(
0,
#1145000
b10011 )
1(
1,
#1150000
0(
0,
#1155000
b10100 )
1(
1,
#1160000
0(
0,
#1165000
1+
1'
b10101 )
1(
1,
#1170000
0(
0,
#1175000
0+
0'
b10110 )
b100 6
1(
1,
#1180000
0(
0,
#1185000
b10111 )
1(
1,
#1190000
0(
0,
#1195000
b11000 )
1(
1,
#1200000
0(
0,
#1205000
b11001 )
1(
1,
#1210000
0(
0,
#1215000
b11 1
1+
1'
b11010 )
1(
1,
#1220000
0(
0,
#1225000
10
1#
0.
0!
13
1%
b11 5
b0 6
0+
0'
b11011 )
1(
1,
#1230000
0(
0,
#1235000
b11100 )
1(
1,
#1240000
0(
0,
#1245000
b11101 )
1(
1,
#1250000
0(
0,
#1255000
b11110 )
1(
1,
#1260000
0(
0,
#1265000
1+
1'
b11111 )
1(
1,
#1270000
0(
0,
#1275000
0+
0'
b0 )
b1 6
1(
1,
#1280000
0(
0,
#1285000
b0 1
1+
1'
b1 )
1(
1,
#1290000
0(
0,
#1295000
1/
1"
12
1$
00
0#
03
0%
0+
0'
b10 )
b0 6
b0 5
1(
1,
#1300000
0(
0,
#1305000
b11 )
1(
1,
#1310000
0(
0,
#1315000
b100 )
1(
1,
#1320000
0(
0,
#1325000
b101 )
1(
1,
#1330000
0(
0,
#1335000
1+
1'
b110 )
1(
1,
#1340000
0(
0,
#1345000
b1 6
0+
0'
b111 )
1(
1,
#1350000
0(
0,
#1355000
b1000 )
1(
1,
#1360000
0(
0,
#1365000
b1001 )
1(
1,
#1370000
0(
0,
#1375000
b1010 )
1(
1,
#1380000
0(
0,
#1385000
1+
1'
b1011 )
1(
1,
#1390000
0(
0,
#1395000
0+
0'
b1100 )
b10 6
1(
1,
#1400000
0(
0,
#1405000
b1101 )
1(
1,
#1410000
0(
0,
#1415000
b1110 )
1(
1,
#1420000
0(
0,
#1425000
b1111 )
1(
1,
#1430000
0(
0,
#1435000
1+
1'
b10000 )
1(
1,
#1440000
0(
0,
#1445000
b11 6
0+
0'
b10001 )
1(
1,
#1450000
0(
0,
#1455000
b10010 )
1(
1,
#1460000
0(
0,
#1465000
b10011 )
1(
1,
#1470000
0(
0,
#1475000
b10100 )
1(
1,
#1480000
0(
0,
#1485000
1+
1'
b10101 )
1(
1,
#1490000
0(
0,
#1495000
0+
0'
b10110 )
b100 6
1(
1,
#1500000
0(
0,
#1505000
b10111 )
1(
1,
#1510000
0(
0,
#1515000
b11000 )
1(
1,
#1520000
0(
0,
#1525000
b11001 )
1(
1,
#1530000
0(
0,
#1535000
b1 1
1+
1'
b11010 )
1(
1,
#1540000
0(
0,
#1545000
14
1&
1/
1"
02
0$
b1 5
b0 6
0+
0'
b11011 )
1(
1,
#1550000
0(
0,
#1555000
b11100 )
1(
1,
#1560000
0(
0,
#1565000
b11101 )
1(
1,
#1570000
0(
0,
#1575000
b11110 )
1(
1,
#1580000
0(
0,
#1585000
1+
1'
b11111 )
1(
1,
#1590000
0(
0,
#1595000
0+
0'
b0 )
b1 6
1(
1,
#1600000
0(
0,
#1605000
b10 1
1+
1'
b1 )
1(
1,
#1610000
0(
0,
#1615000
13
1%
1.
1!
0/
0"
04
0&
0+
0'
b10 )
b0 6
b10 5
1(
1,
#1620000
0(
0,
#1625000
b11 )
1(
1,
#1630000
0(
0,
#1635000
b100 )
1(
1,
#1640000
0(
0,
#1645000
b101 )
1(
1,
#1650000
0(
0,
#1655000
1+
1'
b110 )
1(
1,
#1660000
0(
0,
#1665000
b1 6
0+
0'
b111 )
1(
1,
#1670000
0(
0,
#1675000
b1000 )
1(
1,
#1680000
0(
0,
#1685000
b1001 )
1(
1,
#1690000
0(
0,
#1695000
b1010 )
1(
1,
#1700000
0(
0,
#1705000
1+
1'
b1011 )
1(
1,
#1710000
0(
0,
#1715000
0+
0'
b1100 )
b10 6
1(
1,
#1720000
0(
0,
#1725000
b1101 )
1(
1,
#1730000
0(
0,
#1735000
b1110 )
1(
1,
#1740000
0(
0,
#1745000
b1111 )
1(
1,
#1750000
0(
0,
#1755000
1+
1'
b10000 )
1(
1,
#1760000
0(
0,
#1765000
b11 6
0+
0'
b10001 )
1(
1,
#1770000
0(
0,
#1775000
b10010 )
1(
1,
#1780000
0(
0,
#1785000
b10011 )
1(
1,
#1790000
0(
0,
#1795000
b10100 )
1(
1,
#1800000
0(
0,
#1805000
1+
1'
b10101 )
1(
1,
#1810000
0(
0,
#1815000
0+
0'
b10110 )
b100 6
1(
1,
#1820000
0(
0,
#1825000
b10111 )
1(
1,
#1830000
0(
0,
#1835000
b11000 )
1(
1,
#1840000
0(
0,
#1845000
b11001 )
1(
1,
#1850000
0(
0,
#1855000
b11 1
1+
1'
b11010 )
1(
1,
#1860000
0(
0,
#1865000
10
1#
0.
0!
13
1%
b11 5
b0 6
0+
0'
b11011 )
1(
1,
#1870000
0(
0,
#1875000
b11100 )
1(
1,
#1880000
0(
0,
#1885000
b11101 )
1(
1,
#1890000
0(
0,
#1895000
b11110 )
1(
1,
#1900000
0(
0,
#1905000
1+
1'
b11111 )
1(
1,
#1910000
0(
0,
#1915000
0+
0'
b0 )
b1 6
1(
1,
#1920000
0(
0,
#1925000
b0 1
1+
1'
b1 )
1(
1,
#1930000
0(
0,
#1935000
1/
1"
12
1$
00
0#
03
0%
0+
0'
b10 )
b0 6
b0 5
1(
1,
#1940000
0(
0,
#1945000
b11 )
1(
1,
#1950000
0(
0,
#1955000
b100 )
1(
1,
#1960000
0(
0,
#1965000
b101 )
1(
1,
#1970000
0(
0,
#1975000
1+
1'
b110 )
1(
1,
#1980000
0(
0,
#1985000
b1 6
0+
0'
b111 )
1(
1,
#1990000
0(
0,
#1995000
b1000 )
1(
1,
#2000000
0(
0,
#2005000
b1001 )
1(
1,
#2010000
0(
0,
#2015000
b1010 )
1(
1,
#2020000
0(
0,
#2025000
1+
1'
b1011 )
1(
1,
#2030000
0(
0,
#2035000
0+
0'
b1100 )
b10 6
1(
1,
#2040000
0(
0,
#2045000
b1101 )
1(
1,
#2050000
0(
0,
#2055000
b1110 )
1(
1,
#2060000
0(
0,
#2065000
b1111 )
1(
1,
#2070000
0(
0,
#2075000
1+
1'
b10000 )
1(
1,
#2080000
0(
0,
#2085000
b11 6
0+
0'
b10001 )
1(
1,
#2090000
0(
0,
#2095000
b10010 )
1(
1,
#2100000
0(
0,
#2105000
b10011 )
1(
1,
#2110000
0(
0,
#2115000
b10100 )
1(
1,
#2120000
0(
0,
#2125000
1+
1'
b10101 )
1(
1,
#2130000
0(
0,
#2135000
0+
0'
b10110 )
b100 6
1(
1,
#2140000
0(
0,
#2145000
b10111 )
1(
1,
#2150000
0(
0,
#2155000
b11000 )
1(
1,
#2160000
0(
0,
#2165000
b11001 )
1(
1,
#2170000
0(
0,
#2175000
b1 1
1+
1'
b11010 )
1(
1,
#2180000
0(
0,
#2185000
14
1&
1/
1"
02
0$
b1 5
b0 6
0+
0'
b11011 )
1(
1,
#2190000
0(
0,
#2195000
b11100 )
1(
1,
#2200000
0(
0,
#2205000
b11101 )
1(
1,
#2210000
0(
0,
#2215000
b11110 )
1(
1,
#2220000
0(
0,
#2225000
1+
1'
b11111 )
1(
1,
#2230000
0(
0,
#2235000
0+
0'
b0 )
b1 6
1(
1,
#2240000
0(
0,
#2245000
b10 1
1+
1'
b1 )
1(
1,
#2250000
0(
0,
#2255000
13
1%
1.
1!
0/
0"
04
0&
0+
0'
b10 )
b0 6
b10 5
1(
1,
#2260000
0(
0,
#2265000
b11 )
1(
1,
#2270000
0(
0,
#2275000
b100 )
1(
1,
#2280000
0(
0,
#2285000
b101 )
1(
1,
#2290000
0(
0,
#2295000
1+
1'
b110 )
1(
1,
#2300000
0(
0,
#2305000
b1 6
0+
0'
b111 )
1(
1,
#2310000
0(
0,
#2315000
b1000 )
1(
1,
#2320000
0(
0,
#2325000
b1001 )
1(
1,
#2330000
0(
0,
#2335000
b1010 )
1(
1,
#2340000
0(
0,
#2345000
1+
1'
b1011 )
1(
1,
#2350000
0(
0,
#2355000
0+
0'
b1100 )
b10 6
1(
1,
#2360000
0(
0,
#2365000
b1101 )
1(
1,
#2370000
0(
0,
#2375000
b1110 )
1(
1,
#2380000
0(
0,
#2385000
b1111 )
1(
1,
#2390000
0(
0,
#2395000
1+
1'
b10000 )
1(
1,
#2400000
0(
0,
#2405000
b11 6
0+
0'
b10001 )
1(
1,
#2410000
0(
0,
#2415000
b10010 )
1(
1,
#2420000
0(
0,
#2425000
b10011 )
1(
1,
#2430000
0(
0,
#2435000
b10100 )
1(
1,
#2440000
0(
0,
#2445000
1+
1'
b10101 )
1(
1,
#2450000
0(
0,
#2455000
0+
0'
b10110 )
b100 6
1(
1,
#2460000
0(
0,
#2465000
b10111 )
1(
1,
#2470000
0(
0,
#2475000
b11000 )
1(
1,
#2480000
0(
0,
#2485000
b11001 )
1(
1,
#2490000
0(
0,
#2495000
b11 1
1+
1'
b11010 )
1(
1,
#2500000
0(
0,
#2505000
10
1#
0.
0!
13
1%
b11 5
b0 6
0+
0'
b11011 )
1(
1,
#2510000
0(
0,
#2515000
b11100 )
1(
1,
#2520000
0(
0,
#2525000
b11101 )
1(
1,
#2530000
0(
0,
#2535000
b11110 )
1(
1,
#2540000
0(
0,
#2545000
1+
1'
b11111 )
1(
1,
#2550000
0(
0,
#2555000
0+
0'
b0 )
b1 6
1(
1,
#2560000
0(
0,
#2565000
b0 1
1+
1'
b1 )
1(
1,
#2570000
0(
0,
#2575000
1/
1"
12
1$
00
0#
03
0%
0+
0'
b10 )
b0 6
b0 5
1(
1,
#2580000
0(
0,
#2585000
b11 )
1(
1,
#2590000
0(
0,
#2595000
b100 )
1(
1,
#2600000
0(
0,
#2605000
b101 )
1(
1,
#2610000
0(
0,
#2615000
1+
1'
b110 )
1(
1,
#2620000
0(
0,
#2625000
b1 6
0+
0'
b111 )
1(
1,
#2630000
0(
0,
#2635000
b1000 )
1(
1,
#2640000
0(
0,
#2645000
b1001 )
1(
1,
#2650000
0(
0,
#2655000
b1010 )
1(
1,
#2660000
0(
0,
#2665000
1+
1'
b1011 )
1(
1,
#2670000
0(
0,
#2675000
0+
0'
b1100 )
b10 6
1(
1,
#2680000
0(
0,
#2685000
b1101 )
1(
1,
#2690000
0(
0,
#2695000
b1110 )
1(
1,
#2700000
0(
0,
#2705000
b1111 )
1(
1,
#2710000
0(
0,
#2715000
1+
1'
b10000 )
1(
1,
#2720000
0(
0,
#2725000
b11 6
0+
0'
b10001 )
1(
1,
#2730000
0(
0,
#2735000
b10010 )
1(
1,
#2740000
0(
0,
#2745000
b10011 )
1(
1,
#2750000
0(
0,
#2755000
b10100 )
1(
1,
#2760000
0(
0,
#2765000
1+
1'
b10101 )
1(
1,
#2770000
0(
0,
#2775000
0+
0'
b10110 )
b100 6
1(
1,
#2780000
0(
0,
#2785000
b10111 )
1(
1,
#2790000
0(
0,
#2795000
b11000 )
1(
1,
#2800000
0(
0,
#2805000
b11001 )
1(
1,
#2810000
0(
0,
#2815000
b1 1
1+
1'
b11010 )
1(
1,
#2820000
0(
0,
#2825000
14
1&
1/
1"
02
0$
b1 5
b0 6
0+
0'
b11011 )
1(
1,
#2830000
0(
0,
#2835000
b11100 )
1(
1,
#2840000
0(
0,
#2845000
b11101 )
1(
1,
#2850000
0(
0,
#2855000
b11110 )
1(
1,
#2860000
0(
0,
#2865000
1+
1'
b11111 )
1(
1,
#2870000
0(
0,
#2875000
0+
0'
b0 )
b1 6
1(
1,
#2880000
0(
0,
#2885000
b10 1
1+
1'
b1 )
1(
1,
#2890000
0(
0,
#2895000
13
1%
1.
1!
0/
0"
04
0&
0+
0'
b10 )
b0 6
b10 5
1(
1,
#2900000
0(
0,
#2905000
b11 )
1(
1,
#2910000
0(
0,
#2915000
b100 )
1(
1,
#2920000
0(
0,
#2925000
b101 )
1(
1,
#2930000
0(
0,
#2935000
1+
1'
b110 )
1(
1,
#2940000
0(
0,
#2945000
b1 6
0+
0'
b111 )
1(
1,
#2950000
0(
0,
#2955000
b1000 )
1(
1,
#2960000
0(
0,
#2965000
b1001 )
1(
1,
#2970000
0(
0,
#2975000
b1010 )
1(
1,
#2980000
0(
0,
#2985000
1+
1'
b1011 )
1(
1,
#2990000
0(
0,
#2995000
0+
0'
b1100 )
b10 6
1(
1,
#3000000
0(
0,
#3005000
b1101 )
1(
1,
#3010000
0(
0,
#3015000
b1110 )
1(
1,
#3020000
0(
0,
#3025000
b1111 )
1(
1,
#3030000
0(
0,
#3035000
1+
1'
b10000 )
1(
1,
#3040000
0(
0,
#3045000
b11 6
0+
0'
b10001 )
1(
1,
#3050000
0(
0,
#3055000
b10010 )
1(
1,
#3060000
0(
0,
#3065000
b10011 )
1(
1,
#3070000
0(
0,
#3075000
b10100 )
1(
1,
#3080000
0(
0,
#3085000
1+
1'
b10101 )
1(
1,
#3090000
0(
0,
#3095000
0+
0'
b10110 )
b100 6
1(
1,
#3100000
0(
0,
#3105000
b10111 )
1(
1,
#3110000
0(
0,
#3115000
b11000 )
1(
1,
#3120000
0(
0,
#3125000
b11001 )
1(
1,
#3130000
0(
0,
#3135000
b11 1
1+
1'
b11010 )
1(
1,
#3140000
0(
0,
#3145000
10
1#
0.
0!
13
1%
b11 5
b0 6
0+
0'
b11011 )
1(
1,
#3150000
0(
0,
#3155000
b11100 )
1(
1,
#3160000
0(
0,
#3165000
b11101 )
1(
1,
#3170000
0(
0,
#3175000
b11110 )
1(
1,
#3180000
0(
0,
#3185000
1+
1'
b11111 )
1(
1,
#3190000
0(
0,
#3195000
0+
0'
b0 )
b1 6
1(
1,
#3200000
0(
0,
#3205000
b0 1
1+
1'
b1 )
1(
1,
#3210000
0(
0,
#3215000
1/
1"
12
1$
00
0#
03
0%
0+
0'
b10 )
b0 6
b0 5
1(
1,
#3220000
0(
0,
#3225000
b11 )
1(
1,
#3230000
0(
0,
#3235000
b100 )
1(
1,
#3240000
0(
0,
#3245000
b101 )
1(
1,
#3250000
0(
0,
#3255000
1+
1'
b110 )
1(
1,
#3260000
0(
0,
#3265000
b1 6
0+
0'
b111 )
1(
1,
#3270000
0(
0,
#3275000
b1000 )
1(
1,
#3280000
0(
0,
#3285000
b1001 )
1(
1,
#3290000
0(
0,
#3295000
b1010 )
1(
1,
#3300000
0(
0,
#3305000
1+
1'
b1011 )
1(
1,
#3310000
0(
0,
#3315000
0+
0'
b1100 )
b10 6
1(
1,
#3320000
0(
0,
#3325000
b1101 )
1(
1,
#3330000
0(
0,
#3335000
b1110 )
1(
1,
#3340000
0(
0,
#3345000
b1111 )
1(
1,
#3350000
0(
0,
#3355000
1+
1'
b10000 )
1(
1,
#3360000
0(
0,
#3365000
b11 6
0+
0'
b10001 )
1(
1,
#3370000
0(
0,
#3375000
b10010 )
1(
1,
#3380000
0(
0,
#3385000
b10011 )
1(
1,
#3390000
0(
0,
#3395000
b10100 )
1(
1,
#3400000
0(
0,
#3405000
1+
1'
b10101 )
1(
1,
#3410000
0(
0,
#3415000
0+
0'
b10110 )
b100 6
1(
1,
#3420000
0(
0,
#3425000
b10111 )
1(
1,
#3430000
0(
0,
#3435000
b11000 )
1(
1,
#3440000
0(
0,
#3445000
b11001 )
1(
1,
#3450000
0(
0,
#3455000
b1 1
1+
1'
b11010 )
1(
1,
#3460000
0(
0,
#3465000
14
1&
1/
1"
02
0$
b1 5
b0 6
0+
0'
b11011 )
1(
1,
#3470000
0(
0,
#3475000
b11100 )
1(
1,
#3480000
0(
0,
#3485000
b11101 )
1(
1,
#3490000
0(
0,
#3495000
b11110 )
1(
1,
#3500000
0(
0,
#3505000
1+
1'
b11111 )
1(
1,
#3510000
0(
0,
#3515000
0+
0'
b0 )
b1 6
1(
1,
#3520000
0(
0,
#3525000
b10 1
1+
1'
b1 )
1(
1,
#3530000
0(
0,
#3535000
13
1%
1.
1!
0/
0"
04
0&
0+
0'
b10 )
b0 6
b10 5
1(
1,
#3540000
0(
0,
#3545000
b11 )
1(
1,
#3550000
0(
0,
#3555000
b100 )
1(
1,
#3560000
0(
0,
#3565000
b101 )
1(
1,
#3570000
0(
0,
#3575000
1+
1'
b110 )
1(
1,
#3580000
0(
0,
#3585000
b1 6
0+
0'
b111 )
1(
1,
#3590000
0(
0,
#3595000
b1000 )
1(
1,
#3600000
0(
0,
#3605000
b1001 )
1(
1,
#3610000
0(
0,
#3615000
b1010 )
1(
1,
#3620000
0(
0,
#3625000
1+
1'
b1011 )
1(
1,
#3630000
0(
0,
#3635000
0+
0'
b1100 )
b10 6
1(
1,
#3640000
0(
0,
#3645000
b1101 )
1(
1,
#3650000
0(
0,
#3655000
b1110 )
1(
1,
#3660000
0(
0,
#3665000
b1111 )
1(
1,
#3670000
0(
0,
#3675000
1+
1'
b10000 )
1(
1,
#3680000
0(
0,
#3685000
b11 6
0+
0'
b10001 )
1(
1,
#3690000
0(
0,
#3695000
b10010 )
1(
1,
#3700000
0(
0,
#3705000
b10011 )
1(
1,
#3710000
0(
0,
#3715000
b10100 )
1(
1,
#3720000
0(
0,
#3725000
1+
1'
b10101 )
1(
1,
#3730000
0(
0,
#3735000
0+
0'
b10110 )
b100 6
1(
1,
#3740000
0(
0,
#3745000
b10111 )
1(
1,
#3750000
0(
0,
#3755000
b11000 )
1(
1,
#3760000
0(
0,
#3765000
b11001 )
1(
1,
#3770000
0(
0,
#3775000
b11 1
1+
1'
b11010 )
1(
1,
#3780000
0(
0,
#3785000
10
1#
0.
0!
13
1%
b11 5
b0 6
0+
0'
b11011 )
1(
1,
#3790000
0(
0,
#3795000
b11100 )
1(
1,
#3800000
0(
0,
#3805000
b11101 )
1(
1,
#3810000
0(
0,
#3815000
b11110 )
1(
1,
#3820000
0(
0,
#3825000
1+
1'
b11111 )
1(
1,
#3830000
0(
0,
#3835000
0+
0'
b0 )
b1 6
1(
1,
#3840000
0(
0,
#3845000
b0 1
1+
1'
b1 )
1(
1,
