fsm-assignments/problem1_seqdet/seq_detect_mealy.v
`timescale 1ns / 1ps

// Sequence detector (Mealy) for pattern 1101
module seq_detect_mealy(
  input  wire clk,
  input  wire rst,
  input  wire din,
  output wire y
);

  //State encoding
  parameter [1:0]
    S0 = 2'b00,    // No start of the sequence detected
    S1 = 2'b01,    // Saw '1'
    S2 = 2'b10,    // Saw "11"
    S3 = 2'b11;    // Saw "110"

  reg [1:0] state, next_state;

  //State register
  always @(posedge clk) begin
    if (rst)
      state <= S0;          // If Reset, go back to start state
    else
      state <= next_state;  // State update
  end

  //Next-state logic
  always @(*) begin
    case (state)
      S0:  next_state = (din) ? S1 : S0;  // If 1 go to S1 else go to S0 (seen 1 then S1)
      S1:  next_state = (din) ? S2 : S0;  // If 1 go to S2 else go to S0 (seen 11 then S2)
      S2:  next_state = (din) ? S2 : S3;  // If 1 stay in S2 or else go to S3 (seen 1"11" so stay in S2, if 0 seen 110 so go to S3)
      S3:  next_state = (din) ? S1 : S0;  // If 1 go to S1 as seen 1101, if 0 go to S0 as seen 1100
      default: next_state = S0;           // safety default
    endcase
  end

  //Mealy output
  // Output will be 1 when state is S3 and the current input is 1.
  assign y = (state == S3) & din;

endmodule

fsm-assignments/problem1_seqdet/tb_seq_detect_mealy.v
`timescale 1ns/1ps

module tb_seq_detect_mealy;
  reg clk, rst, din;
  wire y;

  seq_detect_mealy dut (
    .clk(clk),
    .rst(rst),
    .din(din),
    .y(y)
  );

  //Clock generation: 100 MHz → 10 ns period
  initial clk = 0;
  always #5 clk = ~clk;   // toggle every 5ns → 10ns period

  //Apply stimulus
  reg [19:0] bitstream = 20'b00110011011010011010;  // test input sequence
  integer i;

  initial begin
    $dumpfile("seq_detect_mealy.vcd");
    $dumpvars();

    // Keep reset de-asserted (always 0)
    rst = 0;

    // Start din at 0 before first bit
    din = 0;

    // Wait a little before driving data
    #10;

    //Giving bitstream to fsm, one bit per clock
    for (i = 19; i >= 0; i = i - 1) begin
      @(posedge clk);        // change din in the middle of the cycle
      din = bitstream[i];    // so it is stable at the next posedge
    end

    #50;
    $finish;
  end
endmodule

fsm-assignments/problem1_seqdet/waves/seq_detect_mealy.vcd
$date
	Tue Aug 19 10:55:46 2025
$end
$version
	Icarus Verilog
$end
$timescale
	1ps
$end
$scope module tb_seq_detect_mealy $end
$var wire 1 ! y $end
$var reg 20 " bitstream [19:0] $end
$var reg 1 # clk $end
$var reg 1 $ din $end
$var integer 32 % i [31:0] $end
$var reg 1 & rst $end
$scope module dut $end
$var wire 1 ' clk $end
$var wire 1 ( din $end
$var wire 1 ) rst $end
$var wire 1 ! y $end
$var reg 2 * next_state [1:0] $end
$var reg 2 + state [1:0] $end
$upscope $end
$upscope $end
$enddefinitions $end
#0
$dumpvars
bx +
b0 *
0)
0(
0'
0&
bx %
0$
0#
b110011011010011010 "
0!
$end
#5000
b0 +
1#
1'
#10000
0#
0'
b10011 %
#15000
b10010 %
1#
1'
#20000
0#
0'
#25000
b10001 %
1#
1'
#30000
0#
0'
#35000
b1 *
b10000 %
1$
1(
1#
1'
#40000
0#
0'
#45000
b10 *
b1 +
b1111 %
1#
1'
#50000
0#
0'
#55000
b10 +
b11 *
b1110 %
0$
0(
1#
1'
#60000
0#
0'
#65000
b0 *
b11 +
b1101 %
1#
1'
#70000
0#
0'
#75000
b0 +
0!
b1 *
b1100 %
1$
1(
1#
1'
#80000
0#
0'
#85000
b10 *
b1 +
b1011 %
1#
1'
#90000
0#
0'
#95000
b10 +
b11 *
b1010 %
0$
0(
1#
1'
#100000
0#
0'
#105000
1!
b11 +
b1 *
b1001 %
1$
1(
1#
1'
#110000
0#
0'
#115000
b10 *
0!
b1 +
b1000 %
1#
1'
#120000
0#
0'
#125000
b10 +
b11 *
b111 %
0$
0(
1#
1'
#130000
0#
0'
#135000
1!
b11 +
b1 *
b110 %
1$
1(
1#
1'
#140000
0#
0'
#145000
b1 +
0!
b0 *
b101 %
0$
0(
1#
1'
#150000
0#
0'
#155000
b0 +
b100 %
1#
1'
#160000
0#
0'
#165000
b1 *
b11 %
1$
1(
1#
1'
#170000
0#
0'
#175000
b10 *
b1 +
b10 %
1#
1'
#180000
0#
0'
#185000
b10 +
b11 *
b1 %
0$
0(
1#
1'
#190000
0#
0'
#195000
1!
b11 +
b1 *
b0 %
1$
1(
1#
1'
#200000
0#
0'
#205000
b1 +
0!
b0 *
b11111111111111111111111111111111 %
0$
0(
1#
1'
#210000
0#
0'
#215000
b0 +
1#
1'
