fsm-assignments/problem3_vending/vending_mealy.v
`timescale 1ns / 1ps

module vending_mealy(
  input wire clk,
  input wire rst,
  input wire [1:0] coin,
  output reg dispense,
  output reg chg5
);


  // State encoding using parameters
  parameter S0  = 2'b00;  // Total = 0
  parameter S5  = 2'b01;  // Total = 5
  parameter S10 = 2'b10;  // Total = 10
  parameter S15 = 2'b11;  // Total = 15

  reg [1:0] state, next_state;

  // Sequential state register
  always @(posedge clk) begin
    if (rst)
      state <= S0;
    else
      state <= next_state;
  end

  // Combinational next-state logic + outputs (Mealy)
  always @(*) begin
    //Defaults
    next_state = state;
    dispense   = 0;
    chg5       = 0;

    case (state)
      S0: begin
        if (coin == 2'b01)      next_state = S5;   // +5
        else if (coin == 2'b10) next_state = S10;  // +10
        else if (coin == 2'b00) next_state = S0;   //idle
      end

      S5: begin
        if (coin == 2'b01)      next_state = S10;  // +5
        else if (coin == 2'b10) next_state = S15;  // +10
        else if (coin == 2'b00) next_state = S5;   //idle
      end

      S10: begin
        if (coin == 2'b01)      next_state = S15;  // +5
        else if (coin == 2'b10) begin
          dispense   = 1;                      //Vend at 20
          next_state = S0;
        end
        else if (coin == 2'b00) next_state = S10; //idle
      end

      S15: begin
        if (coin == 2'b01) begin
          dispense   = 1;                      //Vend at 20
          next_state = S0;
        end
        else if (coin == 2'b10) begin
          dispense   = 1;                      //Vend at 25
          chg5       = 1;                      //Return 5
          next_state = S0;
        end
        else if (coin == 2'b00) next_state = S15; //idle
      end
    endcase
  end
endmodule

fsm-assignments/problem3_vending/tb_vending_mealy.v
`timescale 1ns/1ps

module tb_vending_mealy;
  reg clk, rst;
  reg [1:0] coin;
  wire dispense, chg5;

  // Instantiate DUT
  vending_mealy dut(
    .clk(clk),
    .rst(rst),
    .coin(coin),
    .dispense(dispense),
    .chg5(chg5)
  );

  // Clock generation (10 ns period)
  always #5 clk = ~clk;

  initial begin
    $dumpfile("vending_mealy_wave.vcd");
    $dumpvars(0, tb_vending_mealy);

    // Initialize signals
    clk = 0;
    rst = 1;
    coin = 2'b00;

    // Apply reset
    #10;
    rst = 0;

    // Insert 5 -> total = 5
    #10 coin = 2'b01;
    #10 coin = 2'b00;

    // Insert 10 -> total = 15
    #10 coin = 2'b10;
    #10 coin = 2'b00;

    // Insert 5 -> total = 20 -> dispense
    #10 coin = 2'b01;
    #10 coin = 2'b00;

    // Insert 10 -> total = 10
    #10 coin = 2'b10;
    #10 coin = 2'b00;

    // Insert 10 -> total = 20 -> dispense
    #10 coin = 2'b10;
    #10 coin = 2'b00;

    // Insert 15 path: 10 + 10 + 5 = 25 -> dispense + chg5
    #10 coin = 2'b10;   // total = 10
    #10 coin = 2'b00;
    #10 coin = 2'b10;   // total = 20 -> dispense
    #10 coin = 2'b00;

    // Insert sequence 15 + 10 = 25 case
    #10 coin = 2'b10;   // total = 10
    #10 coin = 2'b00;
    #10 coin = 2'b10;   // total = 20 -> dispense
    #10 coin = 2'b00;
    #10 coin = 2'b01;   // start again: 5
    #10 coin = 2'b00;
    #10 coin = 2'b10;   // total = 15
    #10 coin = 2'b00;
    #10 coin = 2'b10;   // total = 25 -> dispense + chg5
    #10 coin = 2'b00;

    // Finish simulation
    #50 $finish;
  end
endmodule

fsm-assignments/problem3_vending/waves/vending_mealy_wave.vcd
$date
	Mon Aug 18 22:41:10 2025
$end
$version
	Icarus Verilog
$end
$timescale
	1ps
$end
$scope module tb_vending_mealy $end
$var wire 1 ! chg5 $end
$var wire 1 " dispense $end
$var reg 1 # clk $end
$var reg 2 $ coin [1:0] $end
$var reg 1 % rst $end
$scope module dut $end
$var wire 1 & clk $end
$var wire 2 ' coin [1:0] $end
$var wire 1 ( rst $end
$var reg 1 ) chg5 $end
$var reg 1 * dispense $end
$var reg 2 + next_state [1:0] $end
$var reg 2 , state [1:0] $end
$upscope $end
$upscope $end
$enddefinitions $end
#0
$dumpvars
bx ,
bx +
0*
0)
1(
b0 '
0&
1%
b0 $
0#
0"
0!
$end
#5000
b0 +
b0 ,
1#
1&
#10000
0#
0&
0%
0(
#15000
1#
1&
#20000
b1 +
0#
0&
b1 $
b1 '
#25000
b10 +
b1 ,
1#
1&
#30000
b1 +
0#
0&
b0 $
b0 '
#35000
1#
1&
#40000
b11 +
0#
0&
b10 $
b10 '
#45000
b0 +
1)
1!
1*
1"
b11 ,
1#
1&
#50000
0)
0!
0*
0"
b11 +
0#
0&
b0 $
b0 '
#55000
1#
1&
#60000
b0 +
1*
1"
0#
0&
b1 $
b1 '
#65000
b1 +
0*
0"
b0 ,
1#
1&
#70000
b0 +
0#
0&
b0 $
b0 '
#75000
1#
1&
#80000
b10 +
0#
0&
b10 $
b10 '
#85000
b0 +
1*
1"
b10 ,
1#
1&
#90000
0*
0"
b10 +
0#
0&
b0 $
b0 '
#95000
1#
1&
#100000
b0 +
1*
1"
0#
0&
b10 $
b10 '
#105000
b10 +
0*
0"
b0 ,
1#
1&
#110000
b0 +
0#
0&
b0 $
b0 '
#115000
1#
1&
#120000
b10 +
0#
0&
b10 $
b10 '
#125000
b0 +
1*
1"
b10 ,
1#
1&
#130000
0*
0"
b10 +
0#
0&
b0 $
b0 '
#135000
1#
1&
#140000
b0 +
1*
1"
0#
0&
b10 $
b10 '
#145000
b10 +
0*
0"
b0 ,
1#
1&
#150000
b0 +
0#
0&
b0 $
b0 '
#155000
1#
1&
#160000
b10 +
0#
0&
b10 $
b10 '
#165000
b0 +
1*
1"
b10 ,
1#
1&
#170000
0*
0"
b10 +
0#
0&
b0 $
b0 '
#175000
1#
1&
#180000
b0 +
1*
1"
0#
0&
b10 $
b10 '
#185000
b10 +
0*
0"
b0 ,
1#
1&
#190000
b0 +
0#
0&
b0 $
b0 '
#195000
1#
1&
#200000
b1 +
0#
0&
b1 $
b1 '
#205000
b10 +
b1 ,
1#
1&
#210000
b1 +
0#
0&
b0 $
b0 '
#215000
1#
1&
#220000
b11 +
0#
0&
b10 $
b10 '
#225000
b0 +
1)
1!
1*
1"
b11 ,
1#
1&
#230000
0)
0!
0*
0"
b11 +
0#
0&
b0 $
b0 '
#235000
1#
1&
#240000
b0 +
1)
1!
1*
1"
0#
0&
b10 $
b10 '
#245000
b10 +
0)
0!
0*
0"
b0 ,
1#
1&
#250000
b0 +
0#
0&
b0 $
b0 '
