fsm-assignments/problem4_link/slave_fsm.v
`timescale 1ns / 1ps
module slave_fsm(
  input wire clk,
  input wire rst,
  input wire req,
  input wire [7:0] data_in,
  output reg ack,
  output reg [7:0] last_byte 
);
  localparam IDLE = 2'b00, ACK_1 = 2'b01, ACK_2 = 2'b10, WAIT_REQ_LOW = 2'b11;

  reg [1:0] state_reg, state_next;

  always @(posedge clk) begin
    if (rst) begin
      state_reg <= IDLE;
      last_byte <= 8'b0;
    end else begin
      state_reg <= state_next;
      if (state_reg == IDLE && req) begin
        last_byte <= data_in; // Latch data
      end
    end
  end

  always @(*) begin
    state_next = state_reg;
    ack = 1'b0;
    case (state_reg)
      IDLE: if (req) state_next = ACK_1;
      ACK_1: begin
        ack = 1'b1;
        state_next = ACK_2;
      end
      ACK_2: begin
        ack = 1'b1;
        state_next = WAIT_REQ_LOW;
      end
      WAIT_REQ_LOW: begin
        if (!req) state_next = IDLE;
      end
    endcase
  end
endmodule

fsm-assignments/problem4_link/master_fsm.v
`timescale 1ns / 1ps

module master_fsm(
  input wire clk,
  input wire rst,
  input wire ack,
  output reg req,
  output reg [7:0] data,
  output reg done
);
  localparam IDLE = 3'b000, DRIVE_DATA = 3'b001, WAIT_ACK = 3'b010,
              WAIT_ACK_LOW = 3'b011, DONE = 3'b100;

  reg [2:0] state_reg, state_next;
  reg [1:0] byte_count_reg, byte_count_next;

  always @(posedge clk) begin
    if (rst) begin
      state_reg <= IDLE;
      byte_count_reg <= 2'b00;
    end else begin
      state_reg <= state_next;
      byte_count_reg <= byte_count_next;
    end
  end

  always @(*) begin
    state_next = state_reg;
    byte_count_next = byte_count_reg;
    req = 1'b0;
    data = 8'hZZ;
    done = 1'b0;

    case (state_reg)
      IDLE: state_next = DRIVE_DATA;
      DRIVE_DATA: begin
        req = 1'b1;
        data = 8'hA0 + byte_count_reg; // Example data A0, A1, A2, A3
        state_next = WAIT_ACK;
      end
      WAIT_ACK: begin
        //req = 1'b1;
        data = 8'hA0 + byte_count_reg;
        if (ack) begin
          state_next = WAIT_ACK_LOW;
          req = 1'b0;
          end
      end
      WAIT_ACK_LOW: begin
        if (!ack) begin
          if (byte_count_reg == 2'd3) state_next = DONE;
          else begin
            state_next = DRIVE_DATA;
            byte_count_next = byte_count_reg + 1;
          end
        end
      end
      DONE: begin
        done = 1'b1;
        state_next = IDLE;
      end
    endcase
  end
endmodule

fsm-assignments/problem4_link/link_top.v
module link_top (
  input  wire clk,
  input  wire rst,
  output wire done
);

  wire req, ack;
  wire [7:0] data, last_byte;

  master_fsm u_master (
    .clk(clk), .rst(rst), .ack(ack),
    .req(req), .data(data), .done(done)
  );

  slave_fsm u_slave (
    .clk(clk), .rst(rst), .req(req), .data_in(data),
    .ack(ack), .last_byte(last_byte)
  );

endmodule

fsm-assignments/problem4_link/tb_link_top.v
`timescale 1ns / 1ps

module tb_link_top;
  parameter CLK_PERIOD = 10;
  reg clk, rst;
  wire done;

  link_top dut (.clk(clk), .rst(rst), .done(done));

  initial begin
    clk = 0;
    forever #(CLK_PERIOD / 2) clk = ~clk;
  end

  initial begin
    $dumpfile("link.vcd");
    $dumpvars(0, tb_link_top);

    rst = 1;
    repeat(2) @(posedge clk);
    rst = 0;

    // Wait for the 'done' signal to go high
    wait (done);

    @(posedge clk);
    $display("SUCCESS: 4-byte transfer complete at time %0t ns.", $time);
    $finish;
  end
endmodule

fsm-assignments/problem4_link/waves/link.vcd
$date
	Tue Aug 19 13:06:44 2025
$end
$version
	Icarus Verilog
$end
$timescale
	1ps
$end
$scope module tb_link_top $end
$var wire 1 ! done $end
$var reg 1 " clk $end
$var reg 1 # rst $end
$scope module dut $end
$var wire 1 $ ack $end
$var wire 1 % clk $end
$var wire 8 & data [7:0] $end
$var wire 1 ! done $end
$var wire 8 ' last_byte [7:0] $end
$var wire 1 ( req $end
$var wire 1 ) rst $end
$scope module u_master $end
$var wire 1 $ ack $end
$var wire 1 % clk $end
$var wire 1 ) rst $end
$var reg 2 * byte_count_next [1:0] $end
$var reg 2 + byte_count_reg [1:0] $end
$var reg 8 , data [7:0] $end
$var reg 1 - done $end
$var reg 1 . req $end
$var reg 3 / state_next [2:0] $end
$var reg 3 0 state_reg [2:0] $end
$upscope $end
$scope module u_slave $end
$var wire 1 % clk $end
$var wire 8 1 data_in [7:0] $end
$var wire 1 ( req $end
$var wire 1 ) rst $end
$var reg 1 2 ack $end
$var reg 8 3 last_byte [7:0] $end
$var reg 2 4 state_next [1:0] $end
$var reg 2 5 state_reg [1:0] $end
$upscope $end
$upscope $end
$upscope $end
$enddefinitions $end
#0
$dumpvars
bx 5
bx 4
bx 3
x2
bx 1
bx 0
bx /
x.
x-
bx ,
bx +
bx *
1)
x(
bx '
bx &
0%
x$
1#
0"
x!
$end
#5000
0-
0!
bz ,
bz &
bz 1
0.
0(
b0 *
b1 /
02
0$
b0 4
b0 +
b0 0
b0 3
b0 '
b0 5
1"
1%
#10000
0"
0%
#15000
0#
0)
1"
1%
#20000
0"
0%
#25000
b1 4
b10 /
b10100000 ,
b10100000 &
b10100000 1
1.
1(
b1 0
1"
1%
#30000
0"
0%
#35000
b11 /
b10 4
12
1$
b10100000 ,
b10100000 &
b10100000 1
0.
0(
b10100000 3
b10100000 '
b1 5
b10 0
1"
1%
#40000
0"
0%
#45000
bz ,
bz &
bz 1
b11 4
12
1$
b11 0
b10 5
1"
1%
#50000
0"
0%
#55000
b1 *
b1 /
b0 4
02
0$
b11 5
1"
1%
#60000
0"
0%
#65000
b1 4
b10 /
b10100001 ,
b10100001 &
b10100001 1
1.
1(
b1 +
b1 0
b0 5
1"
1%
#70000
0"
0%
#75000
b11 /
b10 4
12
1$
b10100001 ,
b10100001 &
b10100001 1
0.
0(
b10100001 3
b10100001 '
b1 5
b10 0
1"
1%
#80000
0"
0%
#85000
bz ,
bz &
bz 1
b11 4
12
1$
b11 0
b10 5
1"
1%
#90000
0"
0%
#95000
b10 *
b1 /
b0 4
02
0$
b11 5
1"
1%
#100000
0"
0%
#105000
b1 4
b10 /
b10100010 ,
b10100010 &
b10100010 1
1.
1(
b10 +
b1 0
b0 5
1"
1%
#110000
0"
0%
#115000
b11 /
b10 4
12
1$
b10100010 ,
b10100010 &
b10100010 1
0.
0(
b10100010 3
b10100010 '
b1 5
b10 0
1"
1%
#120000
0"
0%
#125000
bz ,
bz &
bz 1
b11 4
12
1$
b11 0
b10 5
1"
1%
#130000
0"
0%
#135000
b11 *
b1 /
b0 4
02
0$
b11 5
1"
1%
#140000
0"
0%
#145000
b1 4
b10 /
b10100011 ,
b10100011 &
b10100011 1
1.
1(
b11 +
b1 0
b0 5
1"
1%
#150000
0"
0%
#155000
b11 /
b10 4
12
1$
b10100011 ,
b10100011 &
b10100011 1
0.
0(
b10100011 3
b10100011 '
b1 5
b10 0
1"
1%
#160000
0"
0%
#165000
bz ,
bz &
bz 1
b11 4
12
1$
b11 0
b10 5
1"
1%
#170000
0"
0%
#175000
b100 /
b0 4
02
0$
b11 5
1"
1%
#180000
0"
0%
#185000
b0 /
1-
1!
b100 0
b0 5
1"
1%
#190000
0"
0%
#195000
b1 /
0-
0!
b0 0
1"
1%
